{
    "title": "A. Vasya and Coins",
    "timeLimit": {
        "value": 1.0,
        "unit": "second"
    },
    "memoryLimit": {
        "value": 256.0,
        "unit": "megabytes"
    },
    "statement": "<p>Vasya decided to go to the grocery store. He found in his wallet $$$a$$$ coins of $$$1$$$ burle and $$$b$$$ coins of $$$2$$$ burles. He does not yet know the total cost of all goods, so help him find out $$$s$$$ ($$$s &gt; 0$$$): the <span class=\"tex-font-style-bf\">minimum</span> positive integer amount of money he <span class=\"tex-font-style-bf\">cannot</span> pay without change or pay at all using only his coins.</p><p>For example, if $$$a=1$$$ and $$$b=1$$$ (he has one $$$1$$$-burle coin and one $$$2$$$-burle coin), then:</p><ul> <li> he can pay $$$1$$$ burle without change, paying with one $$$1$$$-burle coin, </li><li> he can pay $$$2$$$ burle without change, paying with one $$$2$$$-burle coin, </li><li> he can pay $$$3$$$ burle without change by paying with one $$$1$$$-burle coin and one $$$2$$$-burle coin, </li><li> he cannot pay $$$4$$$ burle without change (moreover, he cannot pay this amount at all). </li></ul><p>So for $$$a=1$$$ and $$$b=1$$$ the answer is $$$s=4$$$.</p>",
    "inputSpecification": "<p>The first line of the input contains an integer $$$t$$$ ($$$1 \\le t \\le 10^4$$$) \u2014 the number of test cases in the test.</p><p>The description of each test case consists of one line containing two integers $$$a_i$$$ and $$$b_i$$$ ($$$0 \\le a_i, b_i \\le 10^8$$$)\u00a0\u2014 the number of $$$1$$$-burle coins and $$$2$$$-burles coins Vasya has respectively.</p>",
    "outputSpecification": "<p>For each test case, on a separate line print one integer $$$s$$$ ($$$s &gt; 0$$$): the minimum positive integer amount of money that Vasya cannot pay without change or pay at all.</p>",
    "samples": [
        {
            "input": "\n<div class=\"test-example-line test-example-line-even test-example-line-0\">5</div><div class=\"test-example-line test-example-line-odd test-example-line-1\">1 1</div><div class=\"test-example-line test-example-line-even test-example-line-2\">4 0</div><div class=\"test-example-line test-example-line-odd test-example-line-3\">0 2</div><div class=\"test-example-line test-example-line-even test-example-line-4\">0 0</div><div class=\"test-example-line test-example-line-odd test-example-line-5\">2314 2374</div>",
            "output": "\n4\n5\n1\n1\n7063\n"
        }
    ],
    "note": "<ul> <li> The first test case of the example is clarified into the main part of the statement. </li><li> In the second test case, Vasya has only $$$1$$$ burle coins, and he can collect either any amount from $$$1$$$ to $$$4$$$, but $$$5$$$ can't. </li><li> In the second test case, Vasya has only $$$2$$$ burle coins, and he cannot pay $$$1$$$ burle without change. </li><li> In the fourth test case you don't have any coins, and he can't even pay $$$1$$$ burle. </li></ul>",
    "contestId": 1660,
    "index": "A",
    "name": "Vasya and Coins",
    "type": "PROGRAMMING",
    "tags": [
        "greedy",
        "math"
    ],
    "solvedCount": 35277
}